Workbook
Name LTM_EBITDA: Assumptions!$B$13
Name TaxRate: Assumptions!$B$37
Name ExitMult: Assumptions!$B$41
Name HoldYears: Assumptions!$B$40
Name MinCash: Assumptions!$B$19
Name SponsorEquity: 'Sources & Uses'!$B$15
Name ExitDebt: 'Debt Schedule'!$G$24

Sheet Assumptions
A1: Project SaaSCo — Sponsor LBO (BM-LBO-001) | Assumptions & Drivers
A2: Navigate: | B2: Sources & Uses | C2: Operating Model | D2: Debt Schedule | E2: Returns | F2: Sensitivity
A3: USD millions unless noted. Blue = input, black = calculation, green = link from another sheet.
A4: ENTRY & PURCHASE PRICE
A5: Current share price ($/share) | B5: 4.4
A6: Offer premium (%) | B6: 0.25
A7: Offer price per share ($/share) | B7: =B5*(1+B6) -> 5.5 | C7: offer = $4.40 x (1 + 25%)
A8: Fully diluted shares (m) | B8: 60
A9: Option / RSU buyout ($m) | B9: 0
A10: Equity purchase price ($m) | B10: =B7*B8+B9 -> 330
A11: Target net debt at close, refinanced ($m) | B11: 20
A12: Entry enterprise value ($m) | B12: =B10+B11 -> 350
A13: Entry LTM EBITDA ($m) (= FY0) | B13: 35
A14: Implied entry EV / EBITDA (x) | B14: =B12/B13 -> 10
A16: TRANSACTION FEES & MINIMUM CASH
A17: M&A advisory fees ($m) | B17: 7
A18: Financing fees ($m) | B18: 5
A19: Minimum cash funded to balance sheet ($m) | B19: 5
A21: DEBT FINANCING (both tranches bullet, no OID, no floor)
A22: SOFR base rate | B22: 0.04
A23: Senior Term Loan leverage (x LTM EBITDA) | B23: 4.5
A24: Senior Term Loan spread | B24: 0.035
A25: Senior Term Loan all-in rate | B25: =B22+B24 -> 0.075
A26: Senior Term Loan tenor (years, bullet) | B26: 7
A27: Mezzanine Notes leverage (x LTM EBITDA) | B27: 1
A28: Mezzanine Notes spread | B28: 0.07
A29: Mezzanine Notes all-in rate | B29: =B22+B28 -> 0.11
A30: Mezzanine Notes tenor (years, bullet) | B30: 8
A32: OPERATING ASSUMPTIONS
A33: D&A (% of revenue) | B33: 0.04
A34: Maintenance capex (% of revenue) | B34: 0.03
A35: Growth capex (% of revenue) | B35: 0.01
A36: Increase in NWC (% of change in revenue) | B36: 0.05
A37: Cash tax rate (on EBT) | B37: 0.25
A39: EXIT ASSUMPTIONS
A40: Hold period / exit year | B40: 5
A41: Exit EV / EBITDA multiple (strategic sale) | B41: 9
A42: Exit EBITDA basis | B42: Projected Year-5 EBITDA (NOT entry LTM)
A43: Conventions | B43: No cash sweep / revolver / recap / PIK. Bullet debt -> exit debt = face. Accumulated cash EXCLUDED from exit equity bridge (conservative).

Sheet Sources & Uses
A1: Project SaaSCo — Sponsor LBO (BM-LBO-001) | Sources & Uses at Close
A2: Navigate: | B2: Assumptions | C2: Operating Model | D2: Debt Schedule | E2: Returns | F2: Sensitivity
A3: USD millions unless noted. Blue = input, black = calculation, green = link from another sheet.
A4: USES ($m) | B4: $m | C4: % of total
A5: Equity purchase price | B5: =Assumptions!B10 -> 330 | C5: =B5/$B$10 -> 0.89918256
A6: Refinance target net debt | B6: =Assumptions!B11 -> 20 | C6: =B6/$B$10 -> 0.054495913
A7: M&A advisory fees | B7: =Assumptions!B17 -> 7 | C7: =B7/$B$10 -> 0.019073569
A8: Financing fees | B8: =Assumptions!B18 -> 5 | C8: =B8/$B$10 -> 0.013623978
A9: Minimum cash funded to balance sheet | B9: =Assumptions!B19 -> 5 | C9: =B9/$B$10 -> 0.013623978
A10: TOTAL USES | B10: =SUM(B5:B9) -> 367 | C10: =B10/$B$10 -> 1
A12: SOURCES ($m) | B12: $m | C12: % of total | D12: x LTM EBITDA | E12: All-in rate
A13: Senior Term Loan (SOFR + 350, bullet, 7-yr) | B13: =Assumptions!B23*Assumptions!B13 -> 157.5 | C13: =B13/$B$16 -> 0.42915531 | D13: =B13/Assumptions!$B$13 -> 4.5 | E13: =Assumptions!B25 -> 0.075
A14: Mezzanine Notes (SOFR + 700, bullet, 8-yr) | B14: =Assumptions!B27*Assumptions!B13 -> 35 | C14: =B14/$B$16 -> 0.095367847 | D14: =B14/Assumptions!$B$13 -> 1 | E14: =Assumptions!B29 -> 0.11
A15: Sponsor equity (balancing plug, new money) | B15: =B10-B13-B14 -> 174.5 | C15: =B15/$B$16 -> 0.47547684 | D15: =B15/Assumptions!$B$13 -> 4.9857143
A16: TOTAL SOURCES | B16: =SUM(B13:B15) -> 367 | C16: =B16/$B$16 -> 1 | D16: =B16/Assumptions!$B$13 -> 10.485714
A18: CHECK: Sources - Uses = 0 | B18: =B16-B10 -> 0 | C18: =IF(ABS(B18)<0.000001,"OK","ERROR") -> OK
A20: Memo: total funded debt at close ($m) | B20: =B13+B14 -> 192.5
A21: Memo: entry leverage (total debt / LTM EBITDA) | B21: =B20/Assumptions!B13 -> 5.5

Sheet Operating Model
A1: Project SaaSCo — Sponsor LBO (BM-LBO-001) | Operating Model & Free Cash Flow
A2: Navigate: | B2: Assumptions | C2: Sources & Uses | D2: Debt Schedule | E2: Returns | F2: Sensitivity
A3: USD millions unless noted. Blue = input, black = calculation, green = link from another sheet.
A4: P&L AND DRIVERS ($m) | B4: FY-2A | C4: FY-1A | D4: FY0A | E4: Year 1 | F4: Year 2 | G4: Year 3 | H4: Year 4 | I4: Year 5
A5: Revenue growth (%) | C5: =C6/B6-1 -> 0.11111111 | D5: =D6/C6-1 -> 0.11111111 | E5: 0.12 | F5: 0.11 | G5: 0.1 | H5: 0.09 | I5: 0.08
A6: Revenue | B6: 81 | C6: 90 | D6: 100 | E6: =D6*(1+E5) -> 112 | F6: =E6*(1+F5) -> 124.32 | G6: =F6*(1+G5) -> 136.752 | H6: =G6*(1+H5) -> 149.05968 | I6: =H6*(1+I5) -> 160.98445
A7: EBITDA margin (%) | B7: =B8/B6 -> 0.32962963 | C7: =C8/C6 -> 0.34 | D7: =D8/D6 -> 0.35 | E7: 0.35 | F7: 0.36 | G7: 0.36 | H7: 0.37 | I7: 0.38
A8: EBITDA | B8: 26.7 | C8: 30.6 | D8: 35 | E8: =E6*E7 -> 39.2 | F8: =F6*F7 -> 44.7552 | G8: =G6*G7 -> 49.23072 | H8: =H6*H7 -> 55.152082 | I8: =I6*I7 -> 61.174093
A9: D&A (4.0% of revenue) | E9: =E6*Assumptions!$B$33 -> 4.48 | F9: =F6*Assumptions!$B$33 -> 4.9728 | G9: =G6*Assumptions!$B$33 -> 5.47008 | H9: =H6*Assumptions!$B$33 -> 5.9623872 | I9: =I6*Assumptions!$B$33 -> 6.4393782
A10: EBIT | E10: =E8-E9 -> 34.72 | F10: =F8-F9 -> 39.7824 | G10: =G8-G9 -> 43.76064 | H10: =H8-H9 -> 49.189694 | I10: =I8-I9 -> 54.734714
A12: FREE CASH FLOW BUILD (hold period; no sweep — cash accumulates on balance sheet)
A13: EBITDA | E13: =E8 -> 39.2 | F13: =F8 -> 44.7552 | G13: =G8 -> 49.23072 | H13: =H8 -> 55.152082 | I13: =I8 -> 61.174093
A14: Less: cash interest (on opening debt balances) | E14: =-'Debt Schedule'!C25 -> -15.6625 | F14: =-'Debt Schedule'!D25 -> -15.6625 | G14: =-'Debt Schedule'!E25 -> -15.6625 | H14: =-'Debt Schedule'!F25 -> -15.6625 | I14: =-'Debt Schedule'!G25 -> -15.6625
A15: Less: cash taxes (25% of EBT, floored at 0) | E15: =-MAX(0,E10+E14)*Assumptions!$B$37 -> -4.764375 | F15: =-MAX(0,F10+F14)*Assumptions!$B$37 -> -6.029975 | G15: =-MAX(0,G10+G14)*Assumptions!$B$37 -> -7.024535 | H15: =-MAX(0,H10+H14)*Assumptions!$B$37 -> -8.3817986 | I15: =-MAX(0,I10+I14)*Assumptions!$B$37 -> -9.7680536
A16: Less: maintenance capex (3.0% of revenue) | E16: =-E6*Assumptions!$B$34 -> -3.36 | F16: =-F6*Assumptions!$B$34 -> -3.7296 | G16: =-G6*Assumptions!$B$34 -> -4.10256 | H16: =-H6*Assumptions!$B$34 -> -4.4717904 | I16: =-I6*Assumptions!$B$34 -> -4.8295336
A17: Less: growth capex (1.0% of revenue) | E17: =-E6*Assumptions!$B$35 -> -1.12 | F17: =-F6*Assumptions!$B$35 -> -1.2432 | G17: =-G6*Assumptions!$B$35 -> -1.36752 | H17: =-H6*Assumptions!$B$35 -> -1.4905968 | I17: =-I6*Assumptions!$B$35 -> -1.6098445
A18: Less: increase in NWC (5.0% of Δrevenue) | E18: =-(E6-D6)*Assumptions!$B$36 -> -0.6 | F18: =-(F6-E6)*Assumptions!$B$36 -> -0.616 | G18: =-(G6-F6)*Assumptions!$B$36 -> -0.6216 | H18: =-(H6-G6)*Assumptions!$B$36 -> -0.615384 | I18: =-(I6-H6)*Assumptions!$B$36 -> -0.59623872
A19: Free cash flow (retained as cash) | E19: =SUM(E13:E18) -> 13.693125 | F19: =SUM(F13:F18) -> 17.473925 | G19: =SUM(G13:G18) -> 20.452005 | H19: =SUM(H13:H18) -> 24.530012 | I19: =SUM(I13:I18) -> 28.707922
A20: Cumulative free cash flow | E20: =E19 -> 13.693125 | F20: =E20+F19 -> 31.16705 | G20: =F20+G19 -> 51.619055 | H20: =G20+H19 -> 76.149067 | I20: =H20+I19 -> 104.85699
A21: Memo: EBT (EBIT - cash interest) | E21: =E10+E14 -> 19.0575 | F21: =F10+F14 -> 24.1199 | G21: =G10+G14 -> 28.09814 | H21: =H10+H14 -> 33.527194 | I21: =I10+I14 -> 39.072214
A23: Note: FCF/covenant schedule is for completeness — bullet debt, no sweep, and the cash-excluded exit convention mean it does not change headline IRR/MoIC.

Sheet Debt Schedule
A1: Project SaaSCo — Sponsor LBO (BM-LBO-001) | Debt Schedule & Credit Statistics
A2: Navigate: | B2: Assumptions | C2: Sources & Uses | D2: Operating Model | E2: Returns | F2: Sensitivity
A3: USD millions unless noted. Blue = input, black = calculation, green = link from another sheet.
A4: DEBT SCHEDULE ($m) | B4: At close | C4: Year 1 | D4: Year 2 | E4: Year 3 | F4: Year 4 | G4: Year 5
A6: SENIOR TERM LOAN — SOFR 4.00% + 350 bps = 7.50% all-in, bullet, 7-yr tenor
A7: Drawdown at close | B7: ='Sources & Uses'!B13 -> 157.5
A8: Opening balance | C8: =B7 -> 157.5 | D8: =C11 -> 157.5 | E8: =D11 -> 157.5 | F8: =E11 -> 157.5 | G8: =F11 -> 157.5
A9: Less: mandatory amortization (bullet) | C9: =0 -> 0 | D9: =0 -> 0 | E9: =0 -> 0 | F9: =0 -> 0 | G9: =0 -> 0
A10: Less: cash sweep (none per deal terms) | C10: =0 -> 0 | D10: =0 -> 0 | E10: =0 -> 0 | F10: =0 -> 0 | G10: =0 -> 0
A11: Closing balance | C11: =C8-C9-C10 -> 157.5 | D11: =D8-D9-D10 -> 157.5 | E11: =E8-E9-E10 -> 157.5 | F11: =F8-F9-F10 -> 157.5 | G11: =G8-G9-G10 -> 157.5
A12: Interest rate (all-in) | C12: =Assumptions!$B$25 -> 0.075 | D12: =Assumptions!$B$25 -> 0.075 | E12: =Assumptions!$B$25 -> 0.075 | F12: =Assumptions!$B$25 -> 0.075 | G12: =Assumptions!$B$25 -> 0.075
A13: Interest expense (on opening balance) | C13: =C8*C12 -> 11.8125 | D13: =D8*D12 -> 11.8125 | E13: =E8*E12 -> 11.8125 | F13: =F8*F12 -> 11.8125 | G13: =G8*G12 -> 11.8125
A15: MEZZANINE NOTES — SOFR 4.00% + 700 bps = 11.00% all-in, bullet, 8-yr tenor
A16: Drawdown at close | B16: ='Sources & Uses'!B14 -> 35
A17: Opening balance | C17: =B16 -> 35 | D17: =C20 -> 35 | E17: =D20 -> 35 | F17: =E20 -> 35 | G17: =F20 -> 35
A18: Less: mandatory amortization (bullet) | C18: =0 -> 0 | D18: =0 -> 0 | E18: =0 -> 0 | F18: =0 -> 0 | G18: =0 -> 0
A19: Less: cash sweep (none per deal terms) | C19: =0 -> 0 | D19: =0 -> 0 | E19: =0 -> 0 | F19: =0 -> 0 | G19: =0 -> 0
A20: Closing balance | C20: =C17-C18-C19 -> 35 | D20: =D17-D18-D19 -> 35 | E20: =E17-E18-E19 -> 35 | F20: =F17-F18-F19 -> 35 | G20: =G17-G18-G19 -> 35
A21: Interest rate (all-in) | C21: =Assumptions!$B$29 -> 0.11 | D21: =Assumptions!$B$29 -> 0.11 | E21: =Assumptions!$B$29 -> 0.11 | F21: =Assumptions!$B$29 -> 0.11 | G21: =Assumptions!$B$29 -> 0.11
A22: Interest expense (on opening balance) | C22: =C17*C21 -> 3.85 | D22: =D17*D21 -> 3.85 | E22: =E17*E21 -> 3.85 | F22: =F17*F21 -> 3.85 | G22: =G17*G21 -> 3.85
A24: TOTAL DEBT (closing balance) | B24: =B7+B16 -> 192.5 | C24: =C11+C20 -> 192.5 | D24: =D11+D20 -> 192.5 | E24: =E11+E20 -> 192.5 | F24: =F11+F20 -> 192.5 | G24: =G11+G20 -> 192.5
A25: TOTAL CASH INTEREST | C25: =C13+C22 -> 15.6625 | D25: =D13+D22 -> 15.6625 | E25: =E13+E22 -> 15.6625 | F25: =F13+F22 -> 15.6625 | G25: =G13+G22 -> 15.6625
A27: CASH ROLL-FORWARD & CREDIT STATISTICS
A28: Opening cash | C28: =B30 -> 5 | D28: =C30 -> 18.693125 | E28: =D30 -> 36.16705 | F28: =E30 -> 56.619055 | G28: =F30 -> 81.149067
A29: Plus: free cash flow (no sweep) | C29: ='Operating Model'!E19 -> 13.693125 | D29: ='Operating Model'!F19 -> 17.473925 | E29: ='Operating Model'!G19 -> 20.452005 | F29: ='Operating Model'!H19 -> 24.530012 | G29: ='Operating Model'!I19 -> 28.707922
A30: Closing cash | B30: =Assumptions!B19 -> 5 | C30: =C28+C29 -> 18.693125 | D30: =D28+D29 -> 36.16705 | E30: =E28+E29 -> 56.619055 | F30: =F28+F29 -> 81.149067 | G30: =G28+G29 -> 109.85699
A31: Net debt (total debt - closing cash) | B31: =B24-B30 -> 187.5 | C31: =C24-C30 -> 173.80687 | D31: =D24-D30 -> 156.33295 | E31: =E24-E30 -> 135.88094 | F31: =F24-F30 -> 111.35093 | G31: =G24-G30 -> 82.643011
A32: Gross leverage (total debt / EBITDA) | B32: =B24/Assumptions!B13 -> 5.5 | C32: =C24/'Operating Model'!E8 -> 4.9107143 | D32: =D24/'Operating Model'!F8 -> 4.3011762 | E32: =E24/'Operating Model'!G8 -> 3.9101602 | F32: =F24/'Operating Model'!H8 -> 3.4903488 | G32: =G24/'Operating Model'!I8 -> 3.1467569
A33: Net leverage (net debt / EBITDA) | B33: =B31/Assumptions!B13 -> 5.3571429 | C33: =C31/'Operating Model'!E8 -> 4.4338489 | D33: =D31/'Operating Model'!F8 -> 3.4930678 | E33: =E31/'Operating Model'!G8 -> 2.7600845 | F33: =F31/'Operating Model'!H8 -> 2.0189797 | G33: =G31/'Operating Model'!I8 -> 1.3509479
A34: Interest coverage (EBITDA / cash interest) | C34: ='Operating Model'!E8/C25 -> 2.5027933 | D34: ='Operating Model'!F8/D25 -> 2.8574749 | E34: ='Operating Model'!G8/E25 -> 3.1432223 | F34: ='Operating Model'!H8/F25 -> 3.5212821 | G34: ='Operating Model'!I8/G25 -> 3.9057681
A36: Note: interest accrues on opening balances. Both tranches bullet with no sweep -> debt outstanding at exit = 192.5 face value.

Sheet Returns
A1: Project SaaSCo — Sponsor LBO (BM-LBO-001) | Exit & Sponsor Returns
A2: Navigate: | B2: Assumptions | C2: Sources & Uses | D2: Operating Model | E2: Debt Schedule | F2: Sensitivity
A3: USD millions unless noted. Blue = input, black = calculation, green = link from another sheet.
A4: EXIT EQUITY BRIDGE (end of Year 5, strategic sale)
A5: Year-5 EBITDA ($m) (exit basis: projected, not entry LTM) | B5: ='Operating Model'!I8 -> 61.174093
A6: Exit EV / EBITDA multiple (x) | B6: =Assumptions!B41 -> 9
A7: Exit enterprise value ($m) | B7: =B5*B6 -> 550.56683
A8: Less: debt outstanding at exit ($m) | B8: =-'Debt Schedule'!G24 -> -192.5
A9: EXIT EQUITY PROCEEDS ($m) | B9: =B7+B8 -> 358.06683
A10: Memo: accumulated balance-sheet cash at exit — EXCLUDED from bridge (conservative convention) | B10: ='Debt Schedule'!G30 -> 109.85699
A12: SPONSOR CASH FLOW SERIES ($m) — no interim distributions
B13: Year 0 | C13: Year 1 | D13: Year 2 | E13: Year 3 | F13: Year 4 | G13: Year 5
A14: Sponsor cash flow | B14: =-'Sources & Uses'!B15 -> -174.5 | C14: =0 -> 0 | D14: =0 -> 0 | E14: =0 -> 0 | F14: =0 -> 0 | G14: =B9 -> 358.06683
A16: RETURNS
A17: Sponsor IRR (annual) | B17: =IRR(B14:G14) -> 0.1546058
A18: Sponsor MoIC (x) | B18: =G14/-B14 -> 2.0519589
A19: Hold period (years) | B19: =Assumptions!B40 -> 5
A20: CHECK: (1+IRR)^hold - MoIC = 0 (single in/out cash flow) | B20: =(1+B17)^B19-B18 -> -7.9936058e-15 | C20: =IF(ABS(B20)<0.0001,"OK","ERROR") -> OK
A22: HEADLINE OUTPUTS (benchmark labels)
A23: sponsor_irr | B23: =B17 -> 0.1546058 | C23: annual IRR, decimal
A24: sponsor_moic | B24: =B18 -> 2.0519589 | C24: exit equity proceeds / sponsor equity
A25: exit_equity_proceeds | B25: =B9 -> 358.06683 | C25: $m; exit EV - debt at exit
A26: sponsor_equity_cheque | B26: ='Sources & Uses'!B15 -> 174.5 | C26: $m; S&U balancing plug

Sheet Sensitivity
A1: Project SaaSCo — Sponsor LBO (BM-LBO-001) | Sensitivity Analysis
A2: Navigate: | B2: Assumptions | C2: Sources & Uses | D2: Operating Model | E2: Debt Schedule | F2: Returns
A3: USD millions unless noted. Blue = input, black = calculation, green = link from another sheet.
A4: SPONSOR IRR — EXIT EV/EBITDA MULTIPLE (rows) x REVENUE GROWTH DELTA, uniform p.a. shift (cols)
A5: Exit multiple \ Δ growth p.a. | B5: -0.02 | C5: -0.01 | D5: 0 | E5: 0.01 | F5: 0.02
A6: 7 | B6: =(($A6*('Operating Model'!$D$6*(1+'Operating Model'!$E$5+B$5)*(1+'Operating Model'!$F$5+B$5)*(1+'Operating Model'!$G$5+B$5)*(1+'Operating Model'!$H$5+B$5)*(1+'Operating Model'!$I$5+B$5))*'Operating Model'!$I$7-ExitDebt)/SponsorEquity)^(1/HoldYears)-1 -> 0.025770332 | C6: =(($A6*('Operating Model'!$D$6*(1+'Operating Model'!$E$5+C$5)*(1+'Operating Model'!$F$5+C$5)*(1+'Operating Model'!$G$5+C$5)*(1+'Operating Model'!$H$5+C$5)*(1+'Operating Model'!$I$5+C$5))*'Operating Model'!$I$7-ExitDebt)/SponsorEquity)^(1/HoldYears)-1 -> 0.044175031 | D6: =(($A6*('Operating Model'!$D$6*(1+'Operating Model'!$E$5+D$5)*(1+'Operating Model'!$F$5+D$5)*(1+'Operating Model'!$G$5+D$5)*(1+'Operating Model'!$H$5+D$5)*(1+'Operating Model'!$I$5+D$5))*'Operating Model'!$I$7-ExitDebt)/SponsorEquity)^(1/HoldYears)-1 -> 0.061988227 | E6: =(($A6*('Operating Model'!$D$6*(1+'Operating Model'!$E$5+E$5)*(1+'Operating Model'!$F$5+E$5)*(1+'Operating Model'!$G$5+E$5)*(1+'Operating Model'!$H$5+E$5)*(1+'Operating Model'!$I$5+E$5))*'Operating Model'!$I$7-ExitDebt)/SponsorEquity)^(1/HoldYears)-1 -> 0.079279457 | F6: =(($A6*('Operating Model'!$D$6*(1+'Operating Model'!$E$5+F$5)*(1+'Operating Model'!$F$5+F$5)*(1+'Operating Model'!$G$5+F$5)*(1+'Operating Model'!$H$5+F$5)*(1+'Operating Model'!$I$5+F$5))*'Operating Model'!$I$7-ExitDebt)/SponsorEquity)^(1/HoldYears)-1 -> 0.096106998
A7: 7.5 | B7: =(($A7*('Operating Model'!$D$6*(1+'Operating Model'!$E$5+B$5)*(1+'Operating Model'!$F$5+B$5)*(1+'Operating Model'!$G$5+B$5)*(1+'Operating Model'!$H$5+B$5)*(1+'Operating Model'!$I$5+B$5))*'Operating Model'!$I$7-ExitDebt)/SponsorEquity)^(1/HoldYears)-1 -> 0.053156616 | C7: =(($A7*('Operating Model'!$D$6*(1+'Operating Model'!$E$5+C$5)*(1+'Operating Model'!$F$5+C$5)*(1+'Operating Model'!$G$5+C$5)*(1+'Operating Model'!$H$5+C$5)*(1+'Operating Model'!$I$5+C$5))*'Operating Model'!$I$7-ExitDebt)/SponsorEquity)^(1/HoldYears)-1 -> 0.070940942 | D7: =(($A7*('Operating Model'!$D$6*(1+'Operating Model'!$E$5+D$5)*(1+'Operating Model'!$F$5+D$5)*(1+'Operating Model'!$G$5+D$5)*(1+'Operating Model'!$H$5+D$5)*(1+'Operating Model'!$I$5+D$5))*'Operating Model'!$I$7-ExitDebt)/SponsorEquity)^(1/HoldYears)-1 -> 0.088220755 | E7: =(($A7*('Operating Model'!$D$6*(1+'Operating Model'!$E$5+E$5)*(1+'Operating Model'!$F$5+E$5)*(1+'Operating Model'!$G$5+E$5)*(1+'Operating Model'!$H$5+E$5)*(1+'Operating Model'!$I$5+E$5))*'Operating Model'!$I$7-ExitDebt)/SponsorEquity)^(1/HoldYears)-1 -> 0.10505169 | F7: =(($A7*('Operating Model'!$D$6*(1+'Operating Model'!$E$5+F$5)*(1+'Operating Model'!$F$5+F$5)*(1+'Operating Model'!$G$5+F$5)*(1+'Operating Model'!$H$5+F$5)*(1+'Operating Model'!$I$5+F$5))*'Operating Model'!$I$7-ExitDebt)/SponsorEquity)^(1/HoldYears)-1 -> 0.12148094
A8: 8 | B8: =(($A8*('Operating Model'!$D$6*(1+'Operating Model'!$E$5+B$5)*(1+'Operating Model'!$F$5+B$5)*(1+'Operating Model'!$G$5+B$5)*(1+'Operating Model'!$H$5+B$5)*(1+'Operating Model'!$I$5+B$5))*'Operating Model'!$I$7-ExitDebt)/SponsorEquity)^(1/HoldYears)-1 -> 0.077959089 | C8: =(($A8*('Operating Model'!$D$6*(1+'Operating Model'!$E$5+C$5)*(1+'Operating Model'!$F$5+C$5)*(1+'Operating Model'!$G$5+C$5)*(1+'Operating Model'!$H$5+C$5)*(1+'Operating Model'!$I$5+C$5))*'Operating Model'!$I$7-ExitDebt)/SponsorEquity)^(1/HoldYears)-1 -> 0.095271073 | D8: =(($A8*('Operating Model'!$D$6*(1+'Operating Model'!$E$5+D$5)*(1+'Operating Model'!$F$5+D$5)*(1+'Operating Model'!$G$5+D$5)*(1+'Operating Model'!$H$5+D$5)*(1+'Operating Model'!$I$5+D$5))*'Operating Model'!$I$7-ExitDebt)/SponsorEquity)^(1/HoldYears)-1 -> 0.1121435 | E8: =(($A8*('Operating Model'!$D$6*(1+'Operating Model'!$E$5+E$5)*(1+'Operating Model'!$F$5+E$5)*(1+'Operating Model'!$G$5+E$5)*(1+'Operating Model'!$H$5+E$5)*(1+'Operating Model'!$I$5+E$5))*'Operating Model'!$I$7-ExitDebt)/SponsorEquity)^(1/HoldYears)-1 -> 0.1286223 | F8: =(($A8*('Operating Model'!$D$6*(1+'Operating Model'!$E$5+F$5)*(1+'Operating Model'!$F$5+F$5)*(1+'Operating Model'!$G$5+F$5)*(1+'Operating Model'!$H$5+F$5)*(1+'Operating Model'!$I$5+F$5))*'Operating Model'!$I$7-ExitDebt)/SponsorEquity)^(1/HoldYears)-1 -> 0.14474682
A9: 8.5 | B9: =(($A9*('Operating Model'!$D$6*(1+'Operating Model'!$E$5+B$5)*(1+'Operating Model'!$F$5+B$5)*(1+'Operating Model'!$G$5+B$5)*(1+'Operating Model'!$H$5+B$5)*(1+'Operating Model'!$I$5+B$5))*'Operating Model'!$I$7-ExitDebt)/SponsorEquity)^(1/HoldYears)-1 -> 0.10066893 | C9: =(($A9*('Operating Model'!$D$6*(1+'Operating Model'!$E$5+C$5)*(1+'Operating Model'!$F$5+C$5)*(1+'Operating Model'!$G$5+C$5)*(1+'Operating Model'!$H$5+C$5)*(1+'Operating Model'!$I$5+C$5))*'Operating Model'!$I$7-ExitDebt)/SponsorEquity)^(1/HoldYears)-1 -> 0.11761369 | D9: =(($A9*('Operating Model'!$D$6*(1+'Operating Model'!$E$5+D$5)*(1+'Operating Model'!$F$5+D$5)*(1+'Operating Model'!$G$5+D$5)*(1+'Operating Model'!$H$5+D$5)*(1+'Operating Model'!$I$5+D$5))*'Operating Model'!$I$7-ExitDebt)/SponsorEquity)^(1/HoldYears)-1 -> 0.13416911 | E9: =(($A9*('Operating Model'!$D$6*(1+'Operating Model'!$E$5+E$5)*(1+'Operating Model'!$F$5+E$5)*(1+'Operating Model'!$G$5+E$5)*(1+'Operating Model'!$H$5+E$5)*(1+'Operating Model'!$I$5+E$5))*'Operating Model'!$I$7-ExitDebt)/SponsorEquity)^(1/HoldYears)-1 -> 0.150374 | F9: =(($A9*('Operating Model'!$D$6*(1+'Operating Model'!$E$5+F$5)*(1+'Operating Model'!$F$5+F$5)*(1+'Operating Model'!$G$5+F$5)*(1+'Operating Model'!$H$5+F$5)*(1+'Operating Model'!$I$5+F$5))*'Operating Model'!$I$7-ExitDebt)/SponsorEquity)^(1/HoldYears)-1 -> 0.16626192
A10: 9 | B10: =(($A10*('Operating Model'!$D$6*(1+'Operating Model'!$E$5+B$5)*(1+'Operating Model'!$F$5+B$5)*(1+'Operating Model'!$G$5+B$5)*(1+'Operating Model'!$H$5+B$5)*(1+'Operating Model'!$I$5+B$5))*'Operating Model'!$I$7-ExitDebt)/SponsorEquity)^(1/HoldYears)-1 -> 0.12164581 | C10: =(($A10*('Operating Model'!$D$6*(1+'Operating Model'!$E$5+C$5)*(1+'Operating Model'!$F$5+C$5)*(1+'Operating Model'!$G$5+C$5)*(1+'Operating Model'!$H$5+C$5)*(1+'Operating Model'!$I$5+C$5))*'Operating Model'!$I$7-ExitDebt)/SponsorEquity)^(1/HoldYears)-1 -> 0.13830055 | D10: =(($A10*('Operating Model'!$D$6*(1+'Operating Model'!$E$5+D$5)*(1+'Operating Model'!$F$5+D$5)*(1+'Operating Model'!$G$5+D$5)*(1+'Operating Model'!$H$5+D$5)*(1+'Operating Model'!$I$5+D$5))*'Operating Model'!$I$7-ExitDebt)/SponsorEquity)^(1/HoldYears)-1 -> 0.1546058 | E10: =(($A10*('Operating Model'!$D$6*(1+'Operating Model'!$E$5+E$5)*(1+'Operating Model'!$F$5+E$5)*(1+'Operating Model'!$G$5+E$5)*(1+'Operating Model'!$H$5+E$5)*(1+'Operating Model'!$I$5+E$5))*'Operating Model'!$I$7-ExitDebt)/SponsorEquity)^(1/HoldYears)-1 -> 0.17059504 | F10: =(($A10*('Operating Model'!$D$6*(1+'Operating Model'!$E$5+F$5)*(1+'Operating Model'!$F$5+F$5)*(1+'Operating Model'!$G$5+F$5)*(1+'Operating Model'!$H$5+F$5)*(1+'Operating Model'!$I$5+F$5))*'Operating Model'!$I$7-ExitDebt)/SponsorEquity)^(1/HoldYears)-1 -> 0.18629741
A11: 9.5 | B11: =(($A11*('Operating Model'!$D$6*(1+'Operating Model'!$E$5+B$5)*(1+'Operating Model'!$F$5+B$5)*(1+'Operating Model'!$G$5+B$5)*(1+'Operating Model'!$H$5+B$5)*(1+'Operating Model'!$I$5+B$5))*'Operating Model'!$I$7-ExitDebt)/SponsorEquity)^(1/HoldYears)-1 -> 0.14116159 | C11: =(($A11*('Operating Model'!$D$6*(1+'Operating Model'!$E$5+C$5)*(1+'Operating Model'!$F$5+C$5)*(1+'Operating Model'!$G$5+C$5)*(1+'Operating Model'!$H$5+C$5)*(1+'Operating Model'!$I$5+C$5))*'Operating Model'!$I$7-ExitDebt)/SponsorEquity)^(1/HoldYears)-1 -> 0.1575845 | D11: =(($A11*('Operating Model'!$D$6*(1+'Operating Model'!$E$5+D$5)*(1+'Operating Model'!$F$5+D$5)*(1+'Operating Model'!$G$5+D$5)*(1+'Operating Model'!$H$5+D$5)*(1+'Operating Model'!$I$5+D$5))*'Operating Model'!$I$7-ExitDebt)/SponsorEquity)^(1/HoldYears)-1 -> 0.1736903 | E11: =(($A11*('Operating Model'!$D$6*(1+'Operating Model'!$E$5+E$5)*(1+'Operating Model'!$F$5+E$5)*(1+'Operating Model'!$G$5+E$5)*(1+'Operating Model'!$H$5+E$5)*(1+'Operating Model'!$I$5+E$5))*'Operating Model'!$I$7-ExitDebt)/SponsorEquity)^(1/HoldYears)-1 -> 0.18950832 | F11: =(($A11*('Operating Model'!$D$6*(1+'Operating Model'!$E$5+F$5)*(1+'Operating Model'!$F$5+F$5)*(1+'Operating Model'!$G$5+F$5)*(1+'Operating Model'!$H$5+F$5)*(1+'Operating Model'!$I$5+F$5))*'Operating Model'!$I$7-ExitDebt)/SponsorEquity)^(1/HoldYears)-1 -> 0.20506422
A12: 10 | B12: =(($A12*('Operating Model'!$D$6*(1+'Operating Model'!$E$5+B$5)*(1+'Operating Model'!$F$5+B$5)*(1+'Operating Model'!$G$5+B$5)*(1+'Operating Model'!$H$5+B$5)*(1+'Operating Model'!$I$5+B$5))*'Operating Model'!$I$7-ExitDebt)/SponsorEquity)^(1/HoldYears)-1 -> 0.15942703 | C12: =(($A12*('Operating Model'!$D$6*(1+'Operating Model'!$E$5+C$5)*(1+'Operating Model'!$F$5+C$5)*(1+'Operating Model'!$G$5+C$5)*(1+'Operating Model'!$H$5+C$5)*(1+'Operating Model'!$I$5+C$5))*'Operating Model'!$I$7-ExitDebt)/SponsorEquity)^(1/HoldYears)-1 -> 0.175663 | D12: =(($A12*('Operating Model'!$D$6*(1+'Operating Model'!$E$5+D$5)*(1+'Operating Model'!$F$5+D$5)*(1+'Operating Model'!$G$5+D$5)*(1+'Operating Model'!$H$5+D$5)*(1+'Operating Model'!$I$5+D$5))*'Operating Model'!$I$7-ExitDebt)/SponsorEquity)^(1/HoldYears)-1 -> 0.19160865 | E12: =(($A12*('Operating Model'!$D$6*(1+'Operating Model'!$E$5+E$5)*(1+'Operating Model'!$F$5+E$5)*(1+'Operating Model'!$G$5+E$5)*(1+'Operating Model'!$H$5+E$5)*(1+'Operating Model'!$I$5+E$5))*'Operating Model'!$I$7-ExitDebt)/SponsorEquity)^(1/HoldYears)-1 -> 0.20729001 | F12: =(($A12*('Operating Model'!$D$6*(1+'Operating Model'!$E$5+F$5)*(1+'Operating Model'!$F$5+F$5)*(1+'Operating Model'!$G$5+F$5)*(1+'Operating Model'!$H$5+F$5)*(1+'Operating Model'!$I$5+F$5))*'Operating Model'!$I$7-ExitDebt)/SponsorEquity)^(1/HoldYears)-1 -> 0.22272996
A13: 10.5 | B13: =(($A13*('Operating Model'!$D$6*(1+'Operating Model'!$E$5+B$5)*(1+'Operating Model'!$F$5+B$5)*(1+'Operating Model'!$G$5+B$5)*(1+'Operating Model'!$H$5+B$5)*(1+'Operating Model'!$I$5+B$5))*'Operating Model'!$I$7-ExitDebt)/SponsorEquity)^(1/HoldYears)-1 -> 0.1766091 | C13: =(($A13*('Operating Model'!$D$6*(1+'Operating Model'!$E$5+C$5)*(1+'Operating Model'!$F$5+C$5)*(1+'Operating Model'!$G$5+C$5)*(1+'Operating Model'!$H$5+C$5)*(1+'Operating Model'!$I$5+C$5))*'Operating Model'!$I$7-ExitDebt)/SponsorEquity)^(1/HoldYears)-1 -> 0.1926934 | D13: =(($A13*('Operating Model'!$D$6*(1+'Operating Model'!$E$5+D$5)*(1+'Operating Model'!$F$5+D$5)*(1+'Operating Model'!$G$5+D$5)*(1+'Operating Model'!$H$5+D$5)*(1+'Operating Model'!$I$5+D$5))*'Operating Model'!$I$7-ExitDebt)/SponsorEquity)^(1/HoldYears)-1 -> 0.20850988 | E13: =(($A13*('Operating Model'!$D$6*(1+'Operating Model'!$E$5+E$5)*(1+'Operating Model'!$F$5+E$5)*(1+'Operating Model'!$G$5+E$5)*(1+'Operating Model'!$H$5+E$5)*(1+'Operating Model'!$I$5+E$5))*'Operating Model'!$I$7-ExitDebt)/SponsorEquity)^(1/HoldYears)-1 -> 0.22408191 | F13: =(($A13*('Operating Model'!$D$6*(1+'Operating Model'!$E$5+F$5)*(1+'Operating Model'!$F$5+F$5)*(1+'Operating Model'!$G$5+F$5)*(1+'Operating Model'!$H$5+F$5)*(1+'Operating Model'!$I$5+F$5))*'Operating Model'!$I$7-ExitDebt)/SponsorEquity)^(1/HoldYears)-1 -> 0.23943009
A14: 11 | B14: =(($A14*('Operating Model'!$D$6*(1+'Operating Model'!$E$5+B$5)*(1+'Operating Model'!$F$5+B$5)*(1+'Operating Model'!$G$5+B$5)*(1+'Operating Model'!$H$5+B$5)*(1+'Operating Model'!$I$5+B$5))*'Operating Model'!$I$7-ExitDebt)/SponsorEquity)^(1/HoldYears)-1 -> 0.19284247 | C14: =(($A14*('Operating Model'!$D$6*(1+'Operating Model'!$E$5+C$5)*(1+'Operating Model'!$F$5+C$5)*(1+'Operating Model'!$G$5+C$5)*(1+'Operating Model'!$H$5+C$5)*(1+'Operating Model'!$I$5+C$5))*'Operating Model'!$I$7-ExitDebt)/SponsorEquity)^(1/HoldYears)-1 -> 0.20880322 | D14: =(($A14*('Operating Model'!$D$6*(1+'Operating Model'!$E$5+D$5)*(1+'Operating Model'!$F$5+D$5)*(1+'Operating Model'!$G$5+D$5)*(1+'Operating Model'!$H$5+D$5)*(1+'Operating Model'!$I$5+D$5))*'Operating Model'!$I$7-ExitDebt)/SponsorEquity)^(1/HoldYears)-1 -> 0.22451534 | E14: =(($A14*('Operating Model'!$D$6*(1+'Operating Model'!$E$5+E$5)*(1+'Operating Model'!$F$5+E$5)*(1+'Operating Model'!$G$5+E$5)*(1+'Operating Model'!$H$5+E$5)*(1+'Operating Model'!$I$5+E$5))*'Operating Model'!$I$7-ExitDebt)/SponsorEquity)^(1/HoldYears)-1 -> 0.23999996 | F14: =(($A14*('Operating Model'!$D$6*(1+'Operating Model'!$E$5+F$5)*(1+'Operating Model'!$F$5+F$5)*(1+'Operating Model'!$G$5+F$5)*(1+'Operating Model'!$H$5+F$5)*(1+'Operating Model'!$I$5+F$5))*'Operating Model'!$I$7-ExitDebt)/SponsorEquity)^(1/HoldYears)-1 -> 0.25527584
A16: CHECK: base-case grid IRR - Returns IRR = 0 | B16: =D10-Returns!B17 -> 8.8817842e-16 | C16: =IF(ABS(B16)<0.0001,"OK","ERROR") -> OK
A18: SPONSOR MoIC (x) — same axes
A19: Exit multiple \ Δ growth p.a. | B19: =B5 -> -0.02 | C19: =C5 -> -0.01 | D19: =D5 -> 0 | E19: =E5 -> 0.01 | F19: =F5 -> 0.02
A20: =A6 -> 7 | B20: =($A20*('Operating Model'!$D$6*(1+'Operating Model'!$E$5+B$19)*(1+'Operating Model'!$F$5+B$19)*(1+'Operating Model'!$G$5+B$19)*(1+'Operating Model'!$H$5+B$19)*(1+'Operating Model'!$I$5+B$19))*'Operating Model'!$I$7-ExitDebt)/SponsorEquity -> 1.1356661 | C20: =($A20*('Operating Model'!$D$6*(1+'Operating Model'!$E$5+C$19)*(1+'Operating Model'!$F$5+C$19)*(1+'Operating Model'!$G$5+C$19)*(1+'Operating Model'!$H$5+C$19)*(1+'Operating Model'!$I$5+C$19))*'Operating Model'!$I$7-ExitDebt)/SponsorEquity -> 1.2412707 | D20: =($A20*('Operating Model'!$D$6*(1+'Operating Model'!$E$5+D$19)*(1+'Operating Model'!$F$5+D$19)*(1+'Operating Model'!$G$5+D$19)*(1+'Operating Model'!$H$5+D$19)*(1+'Operating Model'!$I$5+D$19))*'Operating Model'!$I$7-ExitDebt)/SponsorEquity -> 1.3508232 | E20: =($A20*('Operating Model'!$D$6*(1+'Operating Model'!$E$5+E$19)*(1+'Operating Model'!$F$5+E$19)*(1+'Operating Model'!$G$5+E$19)*(1+'Operating Model'!$H$5+E$19)*(1+'Operating Model'!$I$5+E$19))*'Operating Model'!$I$7-ExitDebt)/SponsorEquity -> 1.4644332 | F20: =($A20*('Operating Model'!$D$6*(1+'Operating Model'!$E$5+F$19)*(1+'Operating Model'!$F$5+F$19)*(1+'Operating Model'!$G$5+F$19)*(1+'Operating Model'!$H$5+F$19)*(1+'Operating Model'!$I$5+F$19))*'Operating Model'!$I$7-ExitDebt)/SponsorEquity -> 1.5822123
A21: =A7 -> 7.5 | B21: =($A21*('Operating Model'!$D$6*(1+'Operating Model'!$E$5+B$19)*(1+'Operating Model'!$F$5+B$19)*(1+'Operating Model'!$G$5+B$19)*(1+'Operating Model'!$H$5+B$19)*(1+'Operating Model'!$I$5+B$19))*'Operating Model'!$I$7-ExitDebt)/SponsorEquity -> 1.2955817 | C21: =($A21*('Operating Model'!$D$6*(1+'Operating Model'!$E$5+C$19)*(1+'Operating Model'!$F$5+C$19)*(1+'Operating Model'!$G$5+C$19)*(1+'Operating Model'!$H$5+C$19)*(1+'Operating Model'!$I$5+C$19))*'Operating Model'!$I$7-ExitDebt)/SponsorEquity -> 1.4087295 | D21: =($A21*('Operating Model'!$D$6*(1+'Operating Model'!$E$5+D$19)*(1+'Operating Model'!$F$5+D$19)*(1+'Operating Model'!$G$5+D$19)*(1+'Operating Model'!$H$5+D$19)*(1+'Operating Model'!$I$5+D$19))*'Operating Model'!$I$7-ExitDebt)/SponsorEquity -> 1.5261071 | E21: =($A21*('Operating Model'!$D$6*(1+'Operating Model'!$E$5+E$19)*(1+'Operating Model'!$F$5+E$19)*(1+'Operating Model'!$G$5+E$19)*(1+'Operating Model'!$H$5+E$19)*(1+'Operating Model'!$I$5+E$19))*'Operating Model'!$I$7-ExitDebt)/SponsorEquity -> 1.6478321 | F21: =($A21*('Operating Model'!$D$6*(1+'Operating Model'!$E$5+F$19)*(1+'Operating Model'!$F$5+F$19)*(1+'Operating Model'!$G$5+F$19)*(1+'Operating Model'!$H$5+F$19)*(1+'Operating Model'!$I$5+F$19))*'Operating Model'!$I$7-ExitDebt)/SponsorEquity -> 1.774024
A22: =A8 -> 8 | B22: =($A22*('Operating Model'!$D$6*(1+'Operating Model'!$E$5+B$19)*(1+'Operating Model'!$F$5+B$19)*(1+'Operating Model'!$G$5+B$19)*(1+'Operating Model'!$H$5+B$19)*(1+'Operating Model'!$I$5+B$19))*'Operating Model'!$I$7-ExitDebt)/SponsorEquity -> 1.4554973 | C22: =($A22*('Operating Model'!$D$6*(1+'Operating Model'!$E$5+C$19)*(1+'Operating Model'!$F$5+C$19)*(1+'Operating Model'!$G$5+C$19)*(1+'Operating Model'!$H$5+C$19)*(1+'Operating Model'!$I$5+C$19))*'Operating Model'!$I$7-ExitDebt)/SponsorEquity -> 1.5761883 | D22: =($A22*('Operating Model'!$D$6*(1+'Operating Model'!$E$5+D$19)*(1+'Operating Model'!$F$5+D$19)*(1+'Operating Model'!$G$5+D$19)*(1+'Operating Model'!$H$5+D$19)*(1+'Operating Model'!$I$5+D$19))*'Operating Model'!$I$7-ExitDebt)/SponsorEquity -> 1.7013911 | E22: =($A22*('Operating Model'!$D$6*(1+'Operating Model'!$E$5+E$19)*(1+'Operating Model'!$F$5+E$19)*(1+'Operating Model'!$G$5+E$19)*(1+'Operating Model'!$H$5+E$19)*(1+'Operating Model'!$I$5+E$19))*'Operating Model'!$I$7-ExitDebt)/SponsorEquity -> 1.831231 | F22: =($A22*('Operating Model'!$D$6*(1+'Operating Model'!$E$5+F$19)*(1+'Operating Model'!$F$5+F$19)*(1+'Operating Model'!$G$5+F$19)*(1+'Operating Model'!$H$5+F$19)*(1+'Operating Model'!$I$5+F$19))*'Operating Model'!$I$7-ExitDebt)/SponsorEquity -> 1.9658357
A23: =A9 -> 8.5 | B23: =($A23*('Operating Model'!$D$6*(1+'Operating Model'!$E$5+B$19)*(1+'Operating Model'!$F$5+B$19)*(1+'Operating Model'!$G$5+B$19)*(1+'Operating Model'!$H$5+B$19)*(1+'Operating Model'!$I$5+B$19))*'Operating Model'!$I$7-ExitDebt)/SponsorEquity -> 1.6154128 | C23: =($A23*('Operating Model'!$D$6*(1+'Operating Model'!$E$5+C$19)*(1+'Operating Model'!$F$5+C$19)*(1+'Operating Model'!$G$5+C$19)*(1+'Operating Model'!$H$5+C$19)*(1+'Operating Model'!$I$5+C$19))*'Operating Model'!$I$7-ExitDebt)/SponsorEquity -> 1.743647 | D23: =($A23*('Operating Model'!$D$6*(1+'Operating Model'!$E$5+D$19)*(1+'Operating Model'!$F$5+D$19)*(1+'Operating Model'!$G$5+D$19)*(1+'Operating Model'!$H$5+D$19)*(1+'Operating Model'!$I$5+D$19))*'Operating Model'!$I$7-ExitDebt)/SponsorEquity -> 1.876675 | E23: =($A23*('Operating Model'!$D$6*(1+'Operating Model'!$E$5+E$19)*(1+'Operating Model'!$F$5+E$19)*(1+'Operating Model'!$G$5+E$19)*(1+'Operating Model'!$H$5+E$19)*(1+'Operating Model'!$I$5+E$19))*'Operating Model'!$I$7-ExitDebt)/SponsorEquity -> 2.0146299 | F23: =($A23*('Operating Model'!$D$6*(1+'Operating Model'!$E$5+F$19)*(1+'Operating Model'!$F$5+F$19)*(1+'Operating Model'!$G$5+F$19)*(1+'Operating Model'!$H$5+F$19)*(1+'Operating Model'!$I$5+F$19))*'Operating Model'!$I$7-ExitDebt)/SponsorEquity -> 2.1576475
A24: =A10 -> 9 | B24: =($A24*('Operating Model'!$D$6*(1+'Operating Model'!$E$5+B$19)*(1+'Operating Model'!$F$5+B$19)*(1+'Operating Model'!$G$5+B$19)*(1+'Operating Model'!$H$5+B$19)*(1+'Operating Model'!$I$5+B$19))*'Operating Model'!$I$7-ExitDebt)/SponsorEquity -> 1.7753284 | C24: =($A24*('Operating Model'!$D$6*(1+'Operating Model'!$E$5+C$19)*(1+'Operating Model'!$F$5+C$19)*(1+'Operating Model'!$G$5+C$19)*(1+'Operating Model'!$H$5+C$19)*(1+'Operating Model'!$I$5+C$19))*'Operating Model'!$I$7-ExitDebt)/SponsorEquity -> 1.9111058 | D24: =($A24*('Operating Model'!$D$6*(1+'Operating Model'!$E$5+D$19)*(1+'Operating Model'!$F$5+D$19)*(1+'Operating Model'!$G$5+D$19)*(1+'Operating Model'!$H$5+D$19)*(1+'Operating Model'!$I$5+D$19))*'Operating Model'!$I$7-ExitDebt)/SponsorEquity -> 2.0519589 | E24: =($A24*('Operating Model'!$D$6*(1+'Operating Model'!$E$5+E$19)*(1+'Operating Model'!$F$5+E$19)*(1+'Operating Model'!$G$5+E$19)*(1+'Operating Model'!$H$5+E$19)*(1+'Operating Model'!$I$5+E$19))*'Operating Model'!$I$7-ExitDebt)/SponsorEquity -> 2.1980289 | F24: =($A24*('Operating Model'!$D$6*(1+'Operating Model'!$E$5+F$19)*(1+'Operating Model'!$F$5+F$19)*(1+'Operating Model'!$G$5+F$19)*(1+'Operating Model'!$H$5+F$19)*(1+'Operating Model'!$I$5+F$19))*'Operating Model'!$I$7-ExitDebt)/SponsorEquity -> 2.3494592
A25: =A11 -> 9.5 | B25: =($A25*('Operating Model'!$D$6*(1+'Operating Model'!$E$5+B$19)*(1+'Operating Model'!$F$5+B$19)*(1+'Operating Model'!$G$5+B$19)*(1+'Operating Model'!$H$5+B$19)*(1+'Operating Model'!$I$5+B$19))*'Operating Model'!$I$7-ExitDebt)/SponsorEquity -> 1.935244 | C25: =($A25*('Operating Model'!$D$6*(1+'Operating Model'!$E$5+C$19)*(1+'Operating Model'!$F$5+C$19)*(1+'Operating Model'!$G$5+C$19)*(1+'Operating Model'!$H$5+C$19)*(1+'Operating Model'!$I$5+C$19))*'Operating Model'!$I$7-ExitDebt)/SponsorEquity -> 2.0785645 | D25: =($A25*('Operating Model'!$D$6*(1+'Operating Model'!$E$5+D$19)*(1+'Operating Model'!$F$5+D$19)*(1+'Operating Model'!$G$5+D$19)*(1+'Operating Model'!$H$5+D$19)*(1+'Operating Model'!$I$5+D$19))*'Operating Model'!$I$7-ExitDebt)/SponsorEquity -> 2.2272429 | E25: =($A25*('Operating Model'!$D$6*(1+'Operating Model'!$E$5+E$19)*(1+'Operating Model'!$F$5+E$19)*(1+'Operating Model'!$G$5+E$19)*(1+'Operating Model'!$H$5+E$19)*(1+'Operating Model'!$I$5+E$19))*'Operating Model'!$I$7-ExitDebt)/SponsorEquity -> 2.3814278 | F25: =($A25*('Operating Model'!$D$6*(1+'Operating Model'!$E$5+F$19)*(1+'Operating Model'!$F$5+F$19)*(1+'Operating Model'!$G$5+F$19)*(1+'Operating Model'!$H$5+F$19)*(1+'Operating Model'!$I$5+F$19))*'Operating Model'!$I$7-ExitDebt)/SponsorEquity -> 2.5412709
A26: =A12 -> 10 | B26: =($A26*('Operating Model'!$D$6*(1+'Operating Model'!$E$5+B$19)*(1+'Operating Model'!$F$5+B$19)*(1+'Operating Model'!$G$5+B$19)*(1+'Operating Model'!$H$5+B$19)*(1+'Operating Model'!$I$5+B$19))*'Operating Model'!$I$7-ExitDebt)/SponsorEquity -> 2.0951595 | C26: =($A26*('Operating Model'!$D$6*(1+'Operating Model'!$E$5+C$19)*(1+'Operating Model'!$F$5+C$19)*(1+'Operating Model'!$G$5+C$19)*(1+'Operating Model'!$H$5+C$19)*(1+'Operating Model'!$I$5+C$19))*'Operating Model'!$I$7-ExitDebt)/SponsorEquity -> 2.2460233 | D26: =($A26*('Operating Model'!$D$6*(1+'Operating Model'!$E$5+D$19)*(1+'Operating Model'!$F$5+D$19)*(1+'Operating Model'!$G$5+D$19)*(1+'Operating Model'!$H$5+D$19)*(1+'Operating Model'!$I$5+D$19))*'Operating Model'!$I$7-ExitDebt)/SponsorEquity -> 2.4025268 | E26: =($A26*('Operating Model'!$D$6*(1+'Operating Model'!$E$5+E$19)*(1+'Operating Model'!$F$5+E$19)*(1+'Operating Model'!$G$5+E$19)*(1+'Operating Model'!$H$5+E$19)*(1+'Operating Model'!$I$5+E$19))*'Operating Model'!$I$7-ExitDebt)/SponsorEquity -> 2.5648267 | F26: =($A26*('Operating Model'!$D$6*(1+'Operating Model'!$E$5+F$19)*(1+'Operating Model'!$F$5+F$19)*(1+'Operating Model'!$G$5+F$19)*(1+'Operating Model'!$H$5+F$19)*(1+'Operating Model'!$I$5+F$19))*'Operating Model'!$I$7-ExitDebt)/SponsorEquity -> 2.7330826
A27: =A13 -> 10.5 | B27: =($A27*('Operating Model'!$D$6*(1+'Operating Model'!$E$5+B$19)*(1+'Operating Model'!$F$5+B$19)*(1+'Operating Model'!$G$5+B$19)*(1+'Operating Model'!$H$5+B$19)*(1+'Operating Model'!$I$5+B$19))*'Operating Model'!$I$7-ExitDebt)/SponsorEquity -> 2.2550751 | C27: =($A27*('Operating Model'!$D$6*(1+'Operating Model'!$E$5+C$19)*(1+'Operating Model'!$F$5+C$19)*(1+'Operating Model'!$G$5+C$19)*(1+'Operating Model'!$H$5+C$19)*(1+'Operating Model'!$I$5+C$19))*'Operating Model'!$I$7-ExitDebt)/SponsorEquity -> 2.413482 | D27: =($A27*('Operating Model'!$D$6*(1+'Operating Model'!$E$5+D$19)*(1+'Operating Model'!$F$5+D$19)*(1+'Operating Model'!$G$5+D$19)*(1+'Operating Model'!$H$5+D$19)*(1+'Operating Model'!$I$5+D$19))*'Operating Model'!$I$7-ExitDebt)/SponsorEquity -> 2.5778107 | E27: =($A27*('Operating Model'!$D$6*(1+'Operating Model'!$E$5+E$19)*(1+'Operating Model'!$F$5+E$19)*(1+'Operating Model'!$G$5+E$19)*(1+'Operating Model'!$H$5+E$19)*(1+'Operating Model'!$I$5+E$19))*'Operating Model'!$I$7-ExitDebt)/SponsorEquity -> 2.7482257 | F27: =($A27*('Operating Model'!$D$6*(1+'Operating Model'!$E$5+F$19)*(1+'Operating Model'!$F$5+F$19)*(1+'Operating Model'!$G$5+F$19)*(1+'Operating Model'!$H$5+F$19)*(1+'Operating Model'!$I$5+F$19))*'Operating Model'!$I$7-ExitDebt)/SponsorEquity -> 2.9248944
A28: =A14 -> 11 | B28: =($A28*('Operating Model'!$D$6*(1+'Operating Model'!$E$5+B$19)*(1+'Operating Model'!$F$5+B$19)*(1+'Operating Model'!$G$5+B$19)*(1+'Operating Model'!$H$5+B$19)*(1+'Operating Model'!$I$5+B$19))*'Operating Model'!$I$7-ExitDebt)/SponsorEquity -> 2.4149907 | C28: =($A28*('Operating Model'!$D$6*(1+'Operating Model'!$E$5+C$19)*(1+'Operating Model'!$F$5+C$19)*(1+'Operating Model'!$G$5+C$19)*(1+'Operating Model'!$H$5+C$19)*(1+'Operating Model'!$I$5+C$19))*'Operating Model'!$I$7-ExitDebt)/SponsorEquity -> 2.5809408 | D28: =($A28*('Operating Model'!$D$6*(1+'Operating Model'!$E$5+D$19)*(1+'Operating Model'!$F$5+D$19)*(1+'Operating Model'!$G$5+D$19)*(1+'Operating Model'!$H$5+D$19)*(1+'Operating Model'!$I$5+D$19))*'Operating Model'!$I$7-ExitDebt)/SponsorEquity -> 2.7530947 | E28: =($A28*('Operating Model'!$D$6*(1+'Operating Model'!$E$5+E$19)*(1+'Operating Model'!$F$5+E$19)*(1+'Operating Model'!$G$5+E$19)*(1+'Operating Model'!$H$5+E$19)*(1+'Operating Model'!$I$5+E$19))*'Operating Model'!$I$7-ExitDebt)/SponsorEquity -> 2.9316246 | F28: =($A28*('Operating Model'!$D$6*(1+'Operating Model'!$E$5+F$19)*(1+'Operating Model'!$F$5+F$19)*(1+'Operating Model'!$G$5+F$19)*(1+'Operating Model'!$H$5+F$19)*(1+'Operating Model'!$I$5+F$19))*'Operating Model'!$I$7-ExitDebt)/SponsorEquity -> 3.1167061
A30: CHECK: base-case grid MoIC - Returns MoIC = 0 | B30: =D24-Returns!B18 -> 0 | C30: =IF(ABS(B30)<0.0001,"OK","ERROR") -> OK
A32: Method: single equity outflow at close and single inflow at exit -> IRR = MoIC^(1/hold)-1 exactly. Each cell recomputes the Year-5 revenue path with a uniform growth shift; bullet debt (192.5) and the 174.5 sponsor cheque are held constant via named ranges.
