Workbook

Sheet Assumptions
A1: Assumptions & Sources — Deal Brief BM-3S-001 (MfgCo, synthetic benchmark)
A2: Every hardcoded input in this workbook lives on this sheet (blue). Source for ALL values: benchmarks/briefs/three_statement_mfg.md (frozen synthetic benchmark inputs; fictional company; USD millions; 365-day year; 8 annual columns: t=0..2 historical, t=3..7 projection).
A3: → Model | B3: → Outputs
A5: HISTORICAL P&L INPUTS ($m) — Brief §1
A6: Item | C6: t=0 | D6: t=1 | E6: t=2 | F6: Source
A7: Revenue (historical) | C7: 540 | D7: 570 | E7: 600 | F7: Brief §1 historicals table
A8: EBITDA (historical) | C8: 70.2 | D8: 76.95 | E8: 84 | F8: Brief §1 historicals table
A10: OPENING BALANCE SHEET (anchors t=0, $m) — Brief §2
A11: Cash | C11: 40 | F11: Brief §2 opening balance sheet
A12: Accounts receivable | C12: 90 | F12: Brief §2 opening balance sheet
A13: Inventory | C13: 75 | F13: Brief §2 opening balance sheet
A14: Net PP&E | C14: 250 | F14: Brief §2 opening balance sheet
A15: Accounts payable | C15: 55 | F15: Brief §2 opening balance sheet
A16: Debt | C16: 180 | F16: Brief §2 opening balance sheet
A17: Equity | C17: 220 | F17: Brief §2 opening balance sheet
A19: PROJECTION DRIVERS (t=3..7) — Brief §3
F20: t=3 | G20: t=4 | H20: t=5 | I20: t=6 | J20: t=7
A21: Revenue growth % | F21: 0.05 | G21: 0.045 | H21: 0.04 | I21: 0.035 | J21: 0.03
A22: EBITDA margin % | F22: 0.14 | G22: 0.145 | H22: 0.15 | I22: 0.15 | J22: 0.15
A24: CONSTANT DRIVERS (apply to all columns t=0..7 unless stated) — Brief §3
A25: D&A (% of revenue) | C25: 0.055 | E25: all columns t=0..7
A26: Interest rate on debt | C26: 0.06 | E26: charged on the OPENING debt balance of the year; t=0 uses the t=0 balance
A27: Tax rate | C27: 0.25 | E27: on positive EBT only
A28: Receivables days (DSO) | C28: 55 | E28: AR_t = revenue_t × 55/365, from t=1 onward
A29: Inventory days | C29: 60 | E29: on REVENUE (stated simplification), from t=1 onward
A30: Payables days | C30: 40 | E30: on REVENUE (stated simplification), from t=1 onward
A31: Capex (% of revenue) | C31: 0.06 | E31: all columns t=0..7
A32: Dividend payout | C32: 0.3 | E32: % of positive net income
A33: Debt amortization per year ($m) | C33: 20 | E33: scheduled; floored at 0; financing outflow in the CFS
A34: Days in year | C34: 365 | E34: 365-day year convention
A36: Held at zero per Brief §3: stock-based compensation, revolver, deferred taxes, NOLs, minority interest.

Sheet Model
A1: MfgCo — Integrated 3-Statement Model (Deal Brief BM-3S-001, synthetic benchmark)
A2: USD millions; 365-day year. Columns t=0..2 historical, t=3..7 projection. All inputs on the Assumptions sheet (green cells link there); every other cell is a live formula.
A3: → Assumptions | B3: → Outputs
A4: Line item ($m unless %) | B4: Driver / convention | C4: t=0 (Hist) | D4: t=1 (Hist) | E4: t=2 (Hist) | F4: t=3 (Proj) | G4: t=4 (Proj) | H4: t=5 (Proj) | I4: t=6 (Proj) | J4: t=7 (Proj)
A5: INCOME STATEMENT (P&L)
A6: Revenue | B6: hist input; proj = prior × (1+growth) | C6: =Assumptions!C7 | D6: =Assumptions!D7 | E6: =Assumptions!E7 | F6: =E6*(1+F7) | G6: =F6*(1+G7) | H6: =G6*(1+H7) | I6: =H6*(1+I7) | J6: =I6*(1+J7)
A7: Revenue growth % | B7: hist = computed; proj = Assumptions §3 | D7: =D6/C6-1 | E7: =E6/D6-1 | F7: =Assumptions!F21 | G7: =Assumptions!G21 | H7: =Assumptions!H21 | I7: =Assumptions!I21 | J7: =Assumptions!J21
A8: EBITDA | B8: hist input; proj = revenue × margin | C8: =Assumptions!C8 | D8: =Assumptions!D8 | E8: =Assumptions!E8 | F8: =F6*F9 | G8: =G6*G9 | H8: =H6*H9 | I8: =I6*I9 | J8: =J6*J9
A9: EBITDA margin % | B9: hist = computed; proj = Assumptions §3 | C9: =C8/C6 | D9: =D8/D6 | E9: =E8/E6 | F9: =Assumptions!F22 | G9: =Assumptions!G22 | H9: =Assumptions!H22 | I9: =Assumptions!I22 | J9: =Assumptions!J22
A10: Less: D&A | B10: 5.5% of revenue | C10: =C6*Assumptions!$C$25 | D10: =D6*Assumptions!$C$25 | E10: =E6*Assumptions!$C$25 | F10: =F6*Assumptions!$C$25 | G10: =G6*Assumptions!$C$25 | H10: =H6*Assumptions!$C$25 | I10: =I6*Assumptions!$C$25 | J10: =J6*Assumptions!$C$25
A11: EBIT | B11: EBITDA − D&A | C11: =C8-C10 | D11: =D8-D10 | E11: =E8-E10 | F11: =F8-F10 | G11: =G8-G10 | H11: =H8-H10 | I11: =I8-I10 | J11: =J8-J10
A12: Less: Interest expense | B12: 6.0% × opening debt (from debt schedule) | C12: =C35 | D12: =D35 | E12: =E35 | F12: =F35 | G12: =G35 | H12: =H35 | I12: =I35 | J12: =J35
A13: EBT (pre-tax income) | B13: EBIT − interest | C13: =C11-C12 | D13: =D11-D12 | E13: =E11-E12 | F13: =F11-F12 | G13: =G11-G12 | H13: =H11-H12 | I13: =I11-I12 | J13: =J11-J12
A14: Less: Taxes | B14: 25% of positive EBT only | C14: =MAX(C13,0)*Assumptions!$C$27 | D14: =MAX(D13,0)*Assumptions!$C$27 | E14: =MAX(E13,0)*Assumptions!$C$27 | F14: =MAX(F13,0)*Assumptions!$C$27 | G14: =MAX(G13,0)*Assumptions!$C$27 | H14: =MAX(H13,0)*Assumptions!$C$27 | I14: =MAX(I13,0)*Assumptions!$C$27 | J14: =MAX(J13,0)*Assumptions!$C$27
A15: Net income | B15: EBT − taxes | C15: =C13-C14 | D15: =D13-D14 | E15: =E13-E14 | F15: =F13-F14 | G15: =G13-G14 | H15: =H13-H14 | I15: =I13-I14 | J15: =J13-J14
A16: Net income margin % | B16: net income / revenue | C16: =C15/C6 | D16: =D15/D6 | E16: =E15/E6 | F16: =F15/F6 | G16: =G15/G6 | H16: =H15/H6 | I16: =I15/I6 | J16: =J15/J6
A18: WORKING CAPITAL SCHEDULE
A19: Accounts receivable | B19: t=0 opening BS; then revenue × DSO/365 (DSO=55) | C19: =Assumptions!C12 | D19: =D6*Assumptions!$C$28/Assumptions!$C$34 | E19: =E6*Assumptions!$C$28/Assumptions!$C$34 | F19: =F6*Assumptions!$C$28/Assumptions!$C$34 | G19: =G6*Assumptions!$C$28/Assumptions!$C$34 | H19: =H6*Assumptions!$C$28/Assumptions!$C$34 | I19: =I6*Assumptions!$C$28/Assumptions!$C$34 | J19: =J6*Assumptions!$C$28/Assumptions!$C$34
A20: Inventory | B20: t=0 opening BS; then revenue × 60/365 (on revenue) | C20: =Assumptions!C13 | D20: =D6*Assumptions!$C$29/Assumptions!$C$34 | E20: =E6*Assumptions!$C$29/Assumptions!$C$34 | F20: =F6*Assumptions!$C$29/Assumptions!$C$34 | G20: =G6*Assumptions!$C$29/Assumptions!$C$34 | H20: =H6*Assumptions!$C$29/Assumptions!$C$34 | I20: =I6*Assumptions!$C$29/Assumptions!$C$34 | J20: =J6*Assumptions!$C$29/Assumptions!$C$34
A21: Accounts payable | B21: t=0 opening BS; then revenue × 40/365 (on revenue) | C21: =Assumptions!C15 | D21: =D6*Assumptions!$C$30/Assumptions!$C$34 | E21: =E6*Assumptions!$C$30/Assumptions!$C$34 | F21: =F6*Assumptions!$C$30/Assumptions!$C$34 | G21: =G6*Assumptions!$C$30/Assumptions!$C$34 | H21: =H6*Assumptions!$C$30/Assumptions!$C$34 | I21: =I6*Assumptions!$C$30/Assumptions!$C$34 | J21: =J6*Assumptions!$C$30/Assumptions!$C$34
A22: Net working capital (AR + Inv − AP) | C22: =C19+C20-C21 | D22: =D19+D20-D21 | E22: =E19+E20-E21 | F22: =F19+F20-F21 | G22: =G19+G20-G21 | H22: =H19+H20-H21 | I22: =I19+I20-I21 | J22: =J19+J20-J21
A23: Increase / (decrease) in NWC | B23: ΔNWC = ΔAR + ΔInv − ΔAP | D23: =D22-C22 | E23: =E22-D22 | F23: =F22-E22 | G23: =G22-F22 | H23: =H22-G22 | I23: =I22-H22 | J23: =J22-I22
A25: PP&E SCHEDULE
A26: Opening net PP&E | B26: prior-year closing | D26: =C29 | E26: =D29 | F26: =E29 | G26: =F29 | H26: =G29 | I26: =H29 | J26: =I29
A27: (+) Capex | B27: 6.0% of revenue | C27: =C6*Assumptions!$C$31 | D27: =D6*Assumptions!$C$31 | E27: =E6*Assumptions!$C$31 | F27: =F6*Assumptions!$C$31 | G27: =G6*Assumptions!$C$31 | H27: =H6*Assumptions!$C$31 | I27: =I6*Assumptions!$C$31 | J27: =J6*Assumptions!$C$31
A28: (−) D&A | B28: from P&L | C28: =C10 | D28: =D10 | E28: =E10 | F28: =F10 | G28: =G10 | H28: =H10 | I28: =I10 | J28: =J10
A29: Closing net PP&E | B29: t=0 opening BS; then open + capex − D&A | C29: =Assumptions!C14 | D29: =D26+D27-D28 | E29: =E26+E27-E28 | F29: =F26+F27-F28 | G29: =G26+G27-G28 | H29: =H26+H27-H28 | I29: =I26+I27-I28 | J29: =J26+J27-J28
A31: DEBT SCHEDULE
A32: Opening debt | B32: t=0 anchor; then prior-year closing | C32: =Assumptions!C16 | D32: =C34 | E32: =D34 | F32: =E34 | G32: =F34 | H32: =G34 | I32: =H34 | J32: =I34
A33: (−) Scheduled amortization | B33: 20.0/yr, floored at 0 (=MIN(20, opening)) | D33: =MIN(Assumptions!$C$33,D32) | E33: =MIN(Assumptions!$C$33,E32) | F33: =MIN(Assumptions!$C$33,F32) | G33: =MIN(Assumptions!$C$33,G32) | H33: =MIN(Assumptions!$C$33,H32) | I33: =MIN(Assumptions!$C$33,I32) | J33: =MIN(Assumptions!$C$33,J32)
A34: Closing debt | B34: max(opening − 20, 0); t=0 = 180.0 | C34: =C32 | D34: =D32-D33 | E34: =E32-E33 | F34: =F32-F33 | G34: =G32-G33 | H34: =H32-H33 | I34: =I32-I33 | J34: =J32-J33
A35: Interest expense | B35: 6.0% × opening debt (t=0 uses t=0 balance) | C35: =C32*Assumptions!$C$26 | D35: =D32*Assumptions!$C$26 | E35: =E32*Assumptions!$C$26 | F35: =F32*Assumptions!$C$26 | G35: =G32*Assumptions!$C$26 | H35: =H32*Assumptions!$C$26 | I35: =I32*Assumptions!$C$26 | J35: =J32*Assumptions!$C$26
A37: EQUITY SCHEDULE
A38: Opening equity | B38: prior-year closing | D38: =C41 | E38: =D41 | F38: =E41 | G38: =F41 | H38: =G41 | I38: =H41 | J38: =I41
A39: (+) Net income | B39: from P&L | C39: =C15 | D39: =D15 | E39: =E15 | F39: =F15 | G39: =G15 | H39: =H15 | I39: =I15 | J39: =J15
A40: (−) Dividends | B40: 30% of positive net income | C40: =MAX(C15,0)*Assumptions!$C$32 | D40: =MAX(D15,0)*Assumptions!$C$32 | E40: =MAX(E15,0)*Assumptions!$C$32 | F40: =MAX(F15,0)*Assumptions!$C$32 | G40: =MAX(G15,0)*Assumptions!$C$32 | H40: =MAX(H15,0)*Assumptions!$C$32 | I40: =MAX(I15,0)*Assumptions!$C$32 | J40: =MAX(J15,0)*Assumptions!$C$32
A41: Closing equity | B41: t=0 opening BS; then open + NI − dividends | C41: =Assumptions!C17 | D41: =D38+D39-D40 | E41: =E38+E39-E40 | F41: =F38+F39-F40 | G41: =G38+G39-G40 | H41: =H38+H39-H40 | I41: =I38+I39-I40 | J41: =J38+J39-J40
A43: CASH FLOW STATEMENT (indirect method; modeled from t=1)
A44: Net income | B44: from P&L | D44: =D15 | E44: =E15 | F44: =F15 | G44: =G15 | H44: =H15 | I44: =I15 | J44: =J15
A45: (+) D&A | B45: non-cash add-back | D45: =D10 | E45: =E10 | F45: =F10 | G45: =G10 | H45: =H10 | I45: =I10 | J45: =J10
A46: (−) Increase in net working capital | B46: −ΔNWC | D46: =-D23 | E46: =-E23 | F46: =-F23 | G46: =-G23 | H46: =-H23 | I46: =-I23 | J46: =-J23
A47: Cash flow from operations (CFO) | B47: operating activities = NI + D&A − ΔNWC | D47: =SUM(D44:D46) | E47: =SUM(E44:E46) | F47: =SUM(F44:F46) | G47: =SUM(G44:G46) | H47: =SUM(H44:H46) | I47: =SUM(I44:I46) | J47: =SUM(J44:J46)
A48: (−) Capex | B48: investing outflow | D48: =-D27 | E48: =-E27 | F48: =-F27 | G48: =-G27 | H48: =-H27 | I48: =-I27 | J48: =-J27
A49: Cash flow from investing (CFI) | B49: investing activities = −capex | D49: =D48 | E49: =E48 | F49: =F48 | G49: =G48 | H49: =H48 | I49: =I48 | J49: =J48
A50: (−) Dividends paid | B50: financing outflow | D50: =-D40 | E50: =-E40 | F50: =-F40 | G50: =-G40 | H50: =-H40 | I50: =-I40 | J50: =-J40
A51: (−) Debt repayment | B51: scheduled amortization, financing outflow | D51: =-D33 | E51: =-E33 | F51: =-F33 | G51: =-G33 | H51: =-H33 | I51: =-I33 | J51: =-J33
A52: Cash flow from financing (CFF) | B52: financing activities = −dividends − repayment | D52: =D50+D51 | E52: =E50+E51 | F52: =F50+F51 | G52: =G50+G51 | H52: =H50+H51 | I52: =I50+I51 | J52: =J50+J51
A53: Net change in cash | B53: CFO + CFI + CFF | D53: =D47+D49+D52 | E53: =E47+E49+E52 | F53: =F47+F49+F52 | G53: =G47+G49+G52 | H53: =H47+H49+H52 | I53: =I47+I49+I52 | J53: =J47+J49+J52
A54: Opening cash | B54: prior-year closing | D54: =C55 | E54: =D55 | F54: =E55 | G54: =F55 | H54: =G55 | I54: =H55 | J54: =I55
A55: Closing cash | B55: t=0 opening BS; then opening + net change | C55: =Assumptions!C11 | D55: =D54+D53 | E55: =E54+E53 | F55: =F54+F53 | G55: =G54+G53 | H55: =H54+H53 | I55: =I54+I53 | J55: =J54+J53
A57: BALANCE SHEET
A58: Cash | B58: from cash flow statement | C58: =C55 | D58: =D55 | E58: =E55 | F58: =F55 | G58: =G55 | H58: =H55 | I58: =I55 | J58: =J55
A59: Accounts receivable | B59: from working capital schedule | C59: =C19 | D59: =D19 | E59: =E19 | F59: =F19 | G59: =G19 | H59: =H19 | I59: =I19 | J59: =J19
A60: Inventory | B60: from working capital schedule | C60: =C20 | D60: =D20 | E60: =E20 | F60: =F20 | G60: =G20 | H60: =H20 | I60: =I20 | J60: =J20
A61: Net PP&E | B61: from PP&E schedule | C61: =C29 | D61: =D29 | E61: =E29 | F61: =F29 | G61: =G29 | H61: =H29 | I61: =I29 | J61: =J29
A62: Total assets | C62: =SUM(C58:C61) | D62: =SUM(D58:D61) | E62: =SUM(E58:E61) | F62: =SUM(F58:F61) | G62: =SUM(G58:G61) | H62: =SUM(H58:H61) | I62: =SUM(I58:I61) | J62: =SUM(J58:J61)
A63: Accounts payable | B63: from working capital schedule | C63: =C21 | D63: =D21 | E63: =E21 | F63: =F21 | G63: =G21 | H63: =H21 | I63: =I21 | J63: =J21
A64: Debt | B64: from debt schedule | C64: =C34 | D64: =D34 | E64: =E34 | F64: =F34 | G64: =G34 | H64: =H34 | I64: =I34 | J64: =J34
A65: Total liabilities | C65: =C63+C64 | D65: =D63+D64 | E65: =E63+E64 | F65: =F63+F64 | G65: =G63+G64 | H65: =H63+H64 | I65: =I63+I64 | J65: =J63+J64
A66: Equity | B66: from equity schedule | C66: =C41 | D66: =D41 | E66: =E41 | F66: =F41 | G66: =G41 | H66: =H41 | I66: =I41 | J66: =J41
A67: Total liabilities & equity | C67: =C65+C66 | D67: =D65+D66 | E67: =E65+E66 | F67: =F65+F66 | G67: =G65+G66 | H67: =H65+H66 | I67: =I65+I66 | J67: =J65+J66
A68: Balance check: assets − (liabilities + equity) | B68: must be ~0 every year | C68: =C62-C67 | D68: =D62-D67 | E68: =E62-E67 | F68: =F62-F67 | G68: =G62-G67 | H68: =H62-H67 | I68: =I62-I67 | J68: =J62-J67
A69: Balance status | B69: OK if |check| ≤ 0.01 | C69: =IF(ABS(C68)<=0.01,"OK","ERROR") | D69: =IF(ABS(D68)<=0.01,"OK","ERROR") | E69: =IF(ABS(E68)<=0.01,"OK","ERROR") | F69: =IF(ABS(F68)<=0.01,"OK","ERROR") | G69: =IF(ABS(G68)<=0.01,"OK","ERROR") | H69: =IF(ABS(H68)<=0.01,"OK","ERROR") | I69: =IF(ABS(I68)<=0.01,"OK","ERROR") | J69: =IF(ABS(J68)<=0.01,"OK","ERROR")

Sheet Outputs
A1: Headline Outputs — BM-3S-001 (final projection year, t=7)
A2: All values are live formula links to the Model sheet. USD millions.
A3: → Assumptions | B3: → Model
A5: Headline key | B5: Description | C5: Value | D5: Units
A6: final_net_income | B6: Net income, final year (t=7) | C6: =Model!J15 | D6: $m
A7: final_total_assets | B7: Total assets, final year (t=7) | C7: =Model!J62 | D7: $m
A8: final_total_liabilities_equity | B8: Total liabilities + equity, final year (t=7) | C8: =Model!J67 | D8: $m
A9: final_balance_check | B9: Assets − (liabilities + equity), final year (must be ~0) | C9: =Model!J68 | D9: $m
A10: final_cash | B10: Ending cash, final year (t=7) | C10: =Model!J58 | D10: $m
A11: final_debt | B11: Ending debt, final year (t=7) (= 180 − 7×20) | C11: =Model!J64 | D11: $m
