Workbook

Sheet Model
A1: MfgCo — Integrated 3-Statement Model (Deal Brief BM-3S-001)
A2: USD millions unless stated · 365-day year · Synthetic benchmark — MfgCo is fictional · Blue = input, Black = formula, Green = cross-sheet link
A4: Fiscal year | B4: FY0 | C4: FY1 | D4: FY2 | E4: FY3 | F4: FY4 | G4: FY5 | H4: FY6 | I4: FY7
A5: Phase (t = 0..7) | B5: Historical | C5: Historical | D5: Historical | E5: Projection | F5: Projection | G5: Projection | H5: Projection | I5: Projection
A7: ASSUMPTIONS & DRIVERS
A8: Revenue growth (% YoY) | C8: =C23/B23-1 | D8: =D23/C23-1 | E8: 0.05 | F8: 0.045 | G8: 0.04 | H8: 0.035 | I8: 0.03
A9: EBITDA margin (%) | B9: =B24/B23 | C9: =C24/C23 | D9: =D24/D23 | E9: 0.14 | F9: 0.145 | G9: 0.15 | H9: 0.15 | I9: 0.15
A11: D&A (% of revenue) | B11: 0.055 | C11: All years t = 0..7
A12: Capex (% of revenue) | B12: 0.06 | C12: All years t = 0..7
A13: Interest rate on debt | B13: 0.06 | C13: On opening debt balance; t=0 charged on the t=0 balance
A14: Tax rate | B14: 0.25 | C14: On positive EBT only
A15: Receivable days (DSO) | B15: 55 | C15: AR = Revenue x DSO/365, from t=1 onward
A16: Inventory days (DIO, on revenue) | B16: 60 | C16: Inventory = Revenue x DIO/365, from t=1 (stated simplification)
A17: Payable days (DPO, on revenue) | B17: 40 | C17: AP = Revenue x DPO/365, from t=1 (stated simplification)
A18: Dividend payout (% of positive NI) | B18: 0.3 | C18: Financing outflow in CFS
A19: Scheduled debt amortization ($m / yr) | B19: 20 | C19: Floored at 0; financing outflow in CFS
A20: Days in year | B20: 365
A22: INCOME STATEMENT
A23: Revenue | B23: 540 | C23: 570 | D23: 600 | E23: =D23*(1+E8) | F23: =E23*(1+F8) | G23: =F23*(1+G8) | H23: =G23*(1+H8) | I23: =H23*(1+I8)
A24: EBITDA | B24: 70.2 | C24: 76.95 | D24: 84 | E24: =E23*E9 | F24: =F23*F9 | G24: =G23*G9 | H24: =H23*H9 | I24: =I23*I9
A25: Less: D&A (5.5% of revenue) | B25: =B23*$B$11 | C25: =C23*$B$11 | D25: =D23*$B$11 | E25: =E23*$B$11 | F25: =F23*$B$11 | G25: =G23*$B$11 | H25: =H23*$B$11 | I25: =I23*$B$11
A26: EBIT | B26: =B24-B25 | C26: =C24-C25 | D26: =D24-D25 | E26: =E24-E25 | F26: =F24-F25 | G26: =G24-G25 | H26: =H24-H25 | I26: =I24-I25
A27: Less: Interest expense (6.0% on opening debt) | B27: =$B$13*B51 | C27: =$B$13*B51 | D27: =$B$13*C51 | E27: =$B$13*D51 | F27: =$B$13*E51 | G27: =$B$13*F51 | H27: =$B$13*G51 | I27: =$B$13*H51
A28: EBT (pre-tax income) | B28: =B26-B27 | C28: =C26-C27 | D28: =D26-D27 | E28: =E26-E27 | F28: =F26-F27 | G28: =G26-G27 | H28: =H26-H27 | I28: =I26-I27
A29: Less: Taxes (25% of positive EBT) | B29: =MAX(0,B28)*$B$14 | C29: =MAX(0,C28)*$B$14 | D29: =MAX(0,D28)*$B$14 | E29: =MAX(0,E28)*$B$14 | F29: =MAX(0,F28)*$B$14 | G29: =MAX(0,G28)*$B$14 | H29: =MAX(0,H28)*$B$14 | I29: =MAX(0,I28)*$B$14
A30: Net income | B30: =B28-B29 | C30: =C28-C29 | D30: =D28-D29 | E30: =E28-E29 | F30: =F28-F29 | G30: =G28-G29 | H30: =H28-H29 | I30: =I28-I29
A31: memo: Net margin (%) | B31: =B30/B23 | C31: =C30/C23 | D31: =D30/D23 | E31: =E30/E23 | F31: =F30/F23 | G31: =G30/G23 | H31: =H30/H23 | I31: =I30/I23
A32: memo: Dividends declared (30% of positive NI) | B32: =$B$18*MAX(0,B30) | C32: =$B$18*MAX(0,C30) | D32: =$B$18*MAX(0,D30) | E32: =$B$18*MAX(0,E30) | F32: =$B$18*MAX(0,F30) | G32: =$B$18*MAX(0,G30) | H32: =$B$18*MAX(0,H30) | I32: =$B$18*MAX(0,I30)
A34: SUPPORTING SCHEDULES
A35: Working capital (days-driven from t = 1; t = 0 anchored to opening balance sheet)
A36: Accounts receivable (DSO 55) | B36: 90 | C36: =C23*$B$15/$B$20 | D36: =D23*$B$15/$B$20 | E36: =E23*$B$15/$B$20 | F36: =F23*$B$15/$B$20 | G36: =G23*$B$15/$B$20 | H36: =H23*$B$15/$B$20 | I36: =I23*$B$15/$B$20
A37: Inventory (DIO 60, on revenue) | B37: 75 | C37: =C23*$B$16/$B$20 | D37: =D23*$B$16/$B$20 | E37: =E23*$B$16/$B$20 | F37: =F23*$B$16/$B$20 | G37: =G23*$B$16/$B$20 | H37: =H23*$B$16/$B$20 | I37: =I23*$B$16/$B$20
A38: Accounts payable (DPO 40, on revenue) | B38: 55 | C38: =C23*$B$17/$B$20 | D38: =D23*$B$17/$B$20 | E38: =E23*$B$17/$B$20 | F38: =F23*$B$17/$B$20 | G38: =G23*$B$17/$B$20 | H38: =H23*$B$17/$B$20 | I38: =I23*$B$17/$B$20
A39: Net working capital (AR + Inv - AP) | B39: =B36+B37-B38 | C39: =C36+C37-C38 | D39: =D36+D37-D38 | E39: =E36+E37-E38 | F39: =F36+F37-F38 | G39: =G36+G37-G38 | H39: =H36+H37-H38 | I39: =I36+I37-I38
A40: Increase / (decrease) in NWC | C40: =C39-B39 | D40: =D39-C39 | E40: =E39-D39 | F40: =F39-E39 | G40: =G39-F39 | H40: =H39-G39 | I40: =I39-H39
A42: Net PP&E roll-forward (PPE_t = PPE_t-1 + capex_t - D&A_t, from t = 1)
A43: Opening net PP&E | C43: =B46 | D43: =C46 | E43: =D46 | F43: =E46 | G43: =F46 | H43: =G46 | I43: =H46
A44: Plus: Capex (6.0% of revenue) | B44: =B23*$B$12 | C44: =C23*$B$12 | D44: =D23*$B$12 | E44: =E23*$B$12 | F44: =F23*$B$12 | G44: =G23*$B$12 | H44: =H23*$B$12 | I44: =I23*$B$12
A45: Less: D&A | B45: =B25 | C45: =C25 | D45: =D25 | E45: =E25 | F45: =F25 | G45: =G25 | H45: =H25 | I45: =I25
A46: Closing net PP&E | B46: 250 | C46: =C43+C44-C45 | D46: =D43+D44-D45 | E46: =E43+E44-E45 | F46: =F43+F44-F45 | G46: =G43+G44-G45 | H46: =H43+H44-H45 | I46: =I43+I44-I45
A48: Debt schedule (debt_t = max(debt_t-1 - 20.0, 0); scheduled amortization)
A49: Opening debt | C49: =B51 | D49: =C51 | E49: =D51 | F49: =E51 | G49: =F51 | H49: =G51 | I49: =H51
A50: Less: Scheduled repayment (min of 20.0 and opening) | C50: =MIN($B$19,C49) | D50: =MIN($B$19,D49) | E50: =MIN($B$19,E49) | F50: =MIN($B$19,F49) | G50: =MIN($B$19,G49) | H50: =MIN($B$19,H49) | I50: =MIN($B$19,I49)
A51: Closing debt | B51: 180 | C51: =C49-C50 | D51: =D49-D50 | E51: =E49-E50 | F51: =F49-F50 | G51: =G49-G50 | H51: =H49-H50 | I51: =I49-I50
A53: Equity roll-forward (equity_t = equity_t-1 + NI_t - dividends_t, from t = 1)
A54: Opening equity | C54: =B57 | D54: =C57 | E54: =D57 | F54: =E57 | G54: =F57 | H54: =G57 | I54: =H57
A55: Plus: Net income | C55: =C30 | D55: =D30 | E55: =E30 | F55: =F30 | G55: =G30 | H55: =H30 | I55: =I30
A56: Less: Dividends | C56: =C32 | D56: =D32 | E56: =E32 | F56: =F32 | G56: =G32 | H56: =H32 | I56: =I32
A57: Closing equity | B57: 220 | C57: =C54+C55-C56 | D57: =D54+D55-D56 | E57: =E54+E55-E56 | F57: =F54+F55-F56 | G57: =G54+G55-G56 | H57: =H54+H55-H56 | I57: =I54+I55-I56
A59: CASH FLOW STATEMENT (indirect) — from t = 1; t = 0 anchored by opening balance sheet
A60: Net income | C60: =C30 | D60: =D30 | E60: =E30 | F60: =F30 | G60: =G30 | H60: =H30 | I60: =I30
A61: Add: D&A | C61: =C25 | D61: =D25 | E61: =E25 | F61: =F25 | G61: =G25 | H61: =H25 | I61: =I25
A62: (Increase) / decrease in net working capital | C62: =-C40 | D62: =-D40 | E62: =-E40 | F62: =-F40 | G62: =-G40 | H62: =-H40 | I62: =-I40
A63: Cash flow from operations (CFO) | C63: =SUM(C60:C62) | D63: =SUM(D60:D62) | E63: =SUM(E60:E62) | F63: =SUM(F60:F62) | G63: =SUM(G60:G62) | H63: =SUM(H60:H62) | I63: =SUM(I60:I62)
A64: Less: Capital expenditure | C64: =-C44 | D64: =-D44 | E64: =-E44 | F64: =-F44 | G64: =-G44 | H64: =-H44 | I64: =-I44
A65: Cash flow from investing (CFI) | C65: =C64 | D65: =D64 | E65: =E64 | F65: =F64 | G65: =G64 | H65: =H64 | I65: =I64
A66: Less: Dividends paid | C66: =-C32 | D66: =-D32 | E66: =-E32 | F66: =-F32 | G66: =-G32 | H66: =-H32 | I66: =-I32
A67: Less: Debt repayment (scheduled amortization) | C67: =-C50 | D67: =-D50 | E67: =-E50 | F67: =-F50 | G67: =-G50 | H67: =-H50 | I67: =-I50
A68: Cash flow from financing (CFF) | C68: =C66+C67 | D68: =D66+D67 | E68: =E66+E67 | F68: =F66+F67 | G68: =G66+G67 | H68: =H66+H67 | I68: =I66+I67
A69: Net change in cash (CFO + CFI + CFF) | C69: =C63+C65+C68 | D69: =D63+D65+D68 | E69: =E63+E65+E68 | F69: =F63+F65+F68 | G69: =G63+G65+G68 | H69: =H63+H65+H68 | I69: =I63+I65+I68
A70: Opening cash | C70: =B71 | D70: =C71 | E70: =D71 | F70: =E71 | G70: =F71 | H70: =G71 | I70: =H71
A71: Closing cash | B71: 40 | C71: =C70+C69 | D71: =D70+D69 | E71: =E70+E69 | F71: =F70+F69 | G71: =G70+G69 | H71: =H70+H69 | I71: =I70+I69
A73: BALANCE SHEET
A74: Cash | B74: =B71 | C74: =C71 | D74: =D71 | E74: =E71 | F74: =F71 | G74: =G71 | H74: =H71 | I74: =I71
A75: Accounts receivable | B75: =B36 | C75: =C36 | D75: =D36 | E75: =E36 | F75: =F36 | G75: =G36 | H75: =H36 | I75: =I36
A76: Inventory | B76: =B37 | C76: =C37 | D76: =D37 | E76: =E37 | F76: =F37 | G76: =G37 | H76: =H37 | I76: =I37
A77: Net PP&E | B77: =B46 | C77: =C46 | D77: =D46 | E77: =E46 | F77: =F46 | G77: =G46 | H77: =H46 | I77: =I46
A78: Total assets | B78: =SUM(B74:B77) | C78: =SUM(C74:C77) | D78: =SUM(D74:D77) | E78: =SUM(E74:E77) | F78: =SUM(F74:F77) | G78: =SUM(G74:G77) | H78: =SUM(H74:H77) | I78: =SUM(I74:I77)
A79: Accounts payable | B79: =B38 | C79: =C38 | D79: =D38 | E79: =E38 | F79: =F38 | G79: =G38 | H79: =H38 | I79: =I38
A80: Debt | B80: =B51 | C80: =C51 | D80: =D51 | E80: =E51 | F80: =F51 | G80: =G51 | H80: =H51 | I80: =I51
A81: Total liabilities | B81: =B79+B80 | C81: =C79+C80 | D81: =D79+D80 | E81: =E79+E80 | F81: =F79+F80 | G81: =G79+G80 | H81: =H79+H80 | I81: =I79+I80
A82: Equity | B82: =B57 | C82: =C57 | D82: =D57 | E82: =E57 | F82: =F57 | G82: =G57 | H82: =H57 | I82: =I57
A83: Total liabilities & equity | B83: =B81+B82 | C83: =C81+C82 | D83: =D81+D82 | E83: =E81+E82 | F83: =F81+F82 | G83: =G81+G82 | H83: =H81+H82 | I83: =I81+I82
A84: BALANCE CHECK: Assets - (Liabilities + Equity) | B84: =B78-B83 | C84: =C78-C83 | D84: =D78-D83 | E84: =E78-E83 | F84: =F78-F83 | G84: =G78-G83 | H84: =H78-H83 | I84: =I78-I83
A85: Check flag (|check| < 0.01) | B85: =IF(ABS(B84)<0.01,"OK","ERROR") | C85: =IF(ABS(C84)<0.01,"OK","ERROR") | D85: =IF(ABS(D84)<0.01,"OK","ERROR") | E85: =IF(ABS(E84)<0.01,"OK","ERROR") | F85: =IF(ABS(F84)<0.01,"OK","ERROR") | G85: =IF(ABS(G84)<0.01,"OK","ERROR") | H85: =IF(ABS(H84)<0.01,"OK","ERROR") | I85: =IF(ABS(I84)<0.01,"OK","ERROR")
A87: HEADLINE OUTPUTS — final projection year (t = 7)
A88: final_net_income | B88: =I30 | C88: Net income, final year ($m)
A89: final_total_assets | B89: =I78 | C89: Total assets, final year ($m)
A90: final_total_liabilities_equity | B90: =I83 | C90: Total liabilities + equity, final year ($m)
A91: final_balance_check | B91: =I84 | C91: Assets - (liabilities + equity), final year (~0)
A92: final_cash | B92: =I74 | C92: Ending cash, final year ($m)
A93: final_debt | B93: =I80 | C93: Ending debt, final year ($m) = 180 - 7 x 20 = 40.0
A95: Mechanics per brief: P&L -> debt roll (max(prev - 20, 0)) -> PP&E roll -> equity roll -> indirect CFS -> cash roll. No plugs: the balance sheet ties through the model's own mechanics.

Sheet Outputs
A1: BM-3S-001 — Headline Outputs (final projection year, t = 7)
A2: All values are live links to the Model sheet.
A4: Label | B4: Value | C4: Description
A5: final_net_income | B5: =Model!I30 | C5: Net income, final year ($m)
A6: final_total_assets | B6: =Model!I78 | C6: Total assets, final year ($m)
A7: final_total_liabilities_equity | B7: =Model!I83 | C7: Total liabilities + equity, final year ($m)
A8: final_balance_check | B8: =Model!I84 | C8: Assets - (liabilities + equity), final year (~0)
A9: final_cash | B9: =Model!I74 | C9: Ending cash, final year ($m)
A10: final_debt | B10: =Model!I80 | C10: Ending debt, final year ($m) = 180 - 7 x 20 = 40.0
